strongarm_dataflow-3.0.0.dist-info/RECORD
strongarm_dataflow-3.0.0.dist-info/WHEEL
strongarm_dataflow-3.0.0.dist-info/LICENSE.txt
strongarm_dataflow-3.0.0.dist-info/top_level.txt
strongarm_dataflow-3.0.0.dist-info/METADATA
strongarm_dataflow-3.0.0.data/data/LICENSE.txt
strongarm_dataflow.libs/libcapstone-cbf7f775.so.4
strongarm_dataflow.libs/libsqlite3-e1b77d21.so.0.8.6
strongarm_dataflow/__init__.py
strongarm_dataflow/py.typed
strongarm_dataflow/register_contents.py
strongarm_dataflow/dataflow.cpython-311-x86_64-linux-gnu.so
